getsome/__init__.py
getsome/cli.py
getsome/configuration.py
getsome/feeds.txt
getsome/getsome.cfg
getsome/core/__init__.py
getsome/core/linkme.py
getsome/core/main.py
getsome/core/rss.py
getsome/core/utils.py
getsome/db/__init__.py
getsome/db/initdb.py
getsome/db/session.py
getsome/models/__init__.py
getsome/models/link.py
getsome/models/metadata.py
getsome/models/rss.py
getsome-0.1.5.dist-info/AUTHORS.rst
getsome-0.1.5.dist-info/LICENSE
getsome-0.1.5.dist-info/METADATA
getsome-0.1.5.dist-info/WHEEL
getsome-0.1.5.dist-info/entry_points.txt
getsome-0.1.5.dist-info/top_level.txt
getsome-0.1.5.dist-info/RECORD
