Metadata-Version: 2.1
Name: getsome
Version: 0.1.5
Summary: Get something interesting to consume on internet
Home-page: https://github.com/ranuzz/getsome
Author: shekhar chandra
Author-email: ranuzz@outlook.com
License: MIT license
Keywords: getsome
Platform: UNKNOWN
Classifier: Development Status :: 2 - Pre-Alpha
Classifier: Intended Audience :: Developers
Classifier: License :: OSI Approved :: MIT License
Classifier: Natural Language :: English
Classifier: Programming Language :: Python :: 3
Classifier: Programming Language :: Python :: 3.6
Classifier: Programming Language :: Python :: 3.7
Classifier: Programming Language :: Python :: 3.8
Requires-Python: >=3.6
Requires-Dist: SQLAlchemy (==1.4.29)
Requires-Dist: click (==7.1.2)
Requires-Dist: feedparser (==6.0.8)
Requires-Dist: requests (==2.27.1)
